arc/__init__.py
arc/_lib/__init__.py
arc/events/__init__.py
arc/http/__init__.py
arc/http/helpers/__init__.py
arc/http/helpers/binary_types.py
arc/http/helpers/parse_body.py
arc/http/helpers/res_fmt.py
arc/http/session/__init__.py
arc/http/session/cookies.py
arc/http/session/ddb.py
arc/http/session/jwe.py
arc/queues/__init__.py
arc/services/__init__.py
arc/tables/__init__.py
arc/ws/__init__.py
architect_functions-1.0.0.dist-info/LICENSE
architect_functions-1.0.0.dist-info/METADATA
architect_functions-1.0.0.dist-info/WHEEL
architect_functions-1.0.0.dist-info/top_level.txt
architect_functions-1.0.0.dist-info/RECORD
