Metadata-Version: 2.1
Name: architect-functions
Version: 1.0.0
Summary: Runtime utility library for Functional Web Apps (FWAs) built with Architect (https://arc.codes)
Project-URL: homepage, https://arc.codes
Project-URL: documentation, https://arc.codes/docs/en/reference/runtime-helpers/python
Project-URL: repository, https://github.com/architect/functions-python
Project-URL: changelog, https://github.com/architect/functions-python/blob/main/changelog.md
Classifier: Intended Audience :: Developers
Classifier: License :: OSI Approved :: Apache Software License
Classifier: Operating System :: OS Independent
Classifier: Programming Language :: Python :: 3
Classifier: Topic :: Database
Classifier: Topic :: Internet :: WWW/HTTP
Classifier: Topic :: Software Development
Requires-Python: >=3.7
License-File: LICENSE
Requires-Dist: cryptography
Requires-Dist: python-jose
Requires-Dist: simplejson
